geoloop/__init__.py
geoloop/configuration.py
geoloop/constants.py
geoloop/axisym/AxisymetricEL.py
geoloop/axisym/__init__.py
geoloop/bin/Flowdatamain.py
geoloop/bin/Lithologymain.py
geoloop/bin/Loadprofilemain.py
geoloop/bin/Plotmain.py
geoloop/bin/Runbatch.py
geoloop/bin/Runmain.py
geoloop/bin/SingleRunSim.py
geoloop/bin/__init__.py
geoloop/cli/__init__.py
geoloop/cli/batch.py
geoloop/cli/main.py
geoloop/geoloopcore/CoaxialPipe.py
geoloop/geoloopcore/CustomPipe.py
geoloop/geoloopcore/__init__.py
geoloop/geoloopcore/b2g.py
geoloop/geoloopcore/b2g_ana.py
geoloop/geoloopcore/boreholedesign.py
geoloop/geoloopcore/getloaddata.py
geoloop/geoloopcore/pyg_ana.py
geoloop/geoloopcore/pygfield_ana.py
geoloop/geoloopcore/simulationparameters.py
geoloop/geoloopcore/soilproperties.py
geoloop/geoloopcore/strat_interpolator.py
geoloop/lithology/__init__.py
geoloop/lithology/plot_lithology.py
geoloop/lithology/process_lithology.py
geoloop/lithology/resources/__init__.py
geoloop/lithology/resources/lithology_properties.xlsx
geoloop/loadflowdata/__init__.py
geoloop/loadflowdata/flow_data.py
geoloop/loadflowdata/loadprofile.py
geoloop/plotting/__init__.py
geoloop/plotting/create_plots.py
geoloop/plotting/load_data.py
geoloop/utils/RunManager.py
geoloop/utils/__init__.py
geoloop/utils/helpers.py
geoloop-1.0.3.dist-info/licenses/LICENSE.md
geoloop-1.0.3.dist-info/METADATA
geoloop-1.0.3.dist-info/WHEEL
geoloop-1.0.3.dist-info/entry_points.txt
geoloop-1.0.3.dist-info/top_level.txt
geoloop-1.0.3.dist-info/RECORD
