Metadata-Version: 2.4
Name: geoloop
Version: 1.0.3
Summary: This is a Python package for simulation of (deep) vertical Borehole Heat Exchanger (BHE) systems
Author-email: Zanne Korevaar <zanne.korevaar@tno.nl>, Jan-Diederik van Wees <jan_diederik.vanwees@tno.nl>
License-Expression: Apache-2.0
Keywords: borehole heat exchanger,BHE,geothermal,ground-source heat pump,deep borehole heat exchanger
Requires-Python: <3.14,>=3.12
License-File: LICENSE.md
Requires-Dist: pygfunction>=2.2.2
Requires-Dist: matplotlib>=3.10.1
Requires-Dist: numpy>=2.2.4
Requires-Dist: scipy>=1.7.3
Requires-Dist: h5py>=3.4.0
Requires-Dist: xarray>=2025.3.1
Requires-Dist: pandas<3,>=2.2.3
Requires-Dist: seaborn>=0.13.2
Requires-Dist: tqdm>=4.67.1
Requires-Dist: netCDF4>=1.7.2
Requires-Dist: SecondaryCoolantProps>=1.3
Requires-Dist: openpyxl>=3.1.5
Requires-Dist: h5netcdf>=1.7.3
Requires-Dist: pathlib>=1.0.1
Requires-Dist: pydantic>=2.12.4
Requires-Dist: typer>=0.20.0
Dynamic: license-file
